Workbook

Sheet README
A1: Literature review tracker - prove-TLA
A2: Two concerns, 125 papers, 10 readers
A4: What this is
A5: A reading tracker for the two open questions on the prove-TLA project:
A6: (1) TRAINING - was the fine-tuning failure a method problem, a corpus problem, or a broken MoE adapter?
A7: (2) CONTAMINATION - how do we prove a holdout is clean, and what claims does the contaminated 206-spec corpus permit?
A9: Every paper here was resolved against the live arXiv API or a publisher page. Titles, authors and
A10: dates are as returned by the source, not typed from memory. The 'Why it matters' and 'Question this
A11: should answer' columns are editorial - argue with them.
A13: How to use it
A14: 1. Open the Roster tab and replace 'Reader 01' ... 'Reader 10' in column B with real names.
A15: Every name in the Papers tab is a lookup on that column, so you only type each name once.
... A43: Built 2026-07-30. Source metadata: arXiv API (export.arxiv.org), retrieved 2026-07-30.

Sheet Roster
A1: Roster - put real names in column B
A2: Column B is the only place a name is typed. Papers column E looks it up by slot, so renaming here renames every assignment. Columns E-J are formulas - do not overwrite.
A4: Slot | B4: Name (EDIT ME) | C4: Theme | D4: Theme name | E4: Papers | F4: P1 | G4: P2 | H4: P3 | I4: Done | J4: % done
A5: R01 | B5: Reader 01 | C5: T1 | D5: TLA+, model checking and the toolchain | E5: =COUNTIF(Papers!$D:$D,$A5) -> 11 | F5: =COUNTIFS(Papers!$D:$D,$A5,Papers!$C:$C,1) -> 4 | G5: =COUNTIFS(Papers!$D:$D,$A5,Papers!$C:$C,2) -> 5 | H5: =COUNTIFS(Papers!$D:$D,$A5,Papers!$C:$C,3) -> 2 | I5: =COUNTIFS(Papers!$D:$D,$A5,Papers!$Q:$Q,"Done") -> 0 | J5: =IFERROR($I5/$E5,0) -> 0
A6: R02 | B6: Reader 02 | C6: T1 | D6: TLA+, model checking and the toolchain | E6: =COUNTIF(Papers!$D:$D,$A6) -> 10 | F6: =COUNTIFS(Papers!$D:$D,$A6,Papers!$C:$C,1) -> 3 | G6: =COUNTIFS(Papers!$D:$D,$A6,Papers!$C:$C,2) -> 5 | H6: =COUNTIFS(Papers!$D:$D,$A6,Papers!$C:$C,3) -> 2 | I6: =COUNTIFS(Papers!$D:$D,$A6,Papers!$Q:$Q,"Done") -> 0 | J6: =IFERROR($I6/$E6,0) -> 0
A7: R03 | B7: Reader 03 | C7: T2 | D7: LLMs x formal verification beyond TLA+ | E7: =COUNTIF(Papers!$D:$D,$A7) -> 14 | F7: =COUNTIFS(Papers!$D:$D,$A7,Papers!$C:$C,1) -> 4 | G7: =COUNTIFS(Papers!$D:$D,$A7,Papers!$C:$C,2) -> 6 | H7: =COUNTIFS(Papers!$D:$D,$A7,Papers!$C:$C,3) -> 4 | I7: =COUNTIFS(Papers!$D:$D,$A7,Papers!$Q:$Q,"Done") -> 0 | J7: =IFERROR($I7/$E7,0) -> 0
A8: R04 | B8: Reader 04 | C8: T2 | D8: LLMs x formal verification beyond TLA+ | E8: =COUNTIF(Papers!$D:$D,$A8) -> 13 | F8: =COUNTIFS(Papers!$D:$D,$A8,Papers!$C:$C,1) -> 4 | G8: =COUNTIFS(Papers!$D:$D,$A8,Papers!$C:$C,2) -> 6 | H8: =COUNTIFS(Papers!$D:$D,$A8,Papers!$C:$C,3) -> 3 | I8: =COUNTIFS(Papers!$D:$D,$A8,Papers!$Q:$Q,"Done") -> 0 | J8: =IFERROR($I8/$E8,0) -> 0
A9: R05 | B9: Reader 05 | C9: T3 | D9: Training: SFT, LoRA/PEFT, MoE adaptation, diversity, corpora | E9: =COUNTIF(Papers!$D:$D,$A9) -> 15 | F9: =COUNTIFS(Papers!$D:$D,$A9,Papers!$C:$C,1) -> 4 | G9: =COUNTIFS(Papers!$D:$D,$A9,Papers!$C:$C,2) -> 5 | H9: =COUNTIFS(Papers!$D:$D,$A9,Papers!$C:$C,3) -> 6 | I9: =COUNTIFS(Papers!$D:$D,$A9,Papers!$Q:$Q,"Done") -> 0 | J9: =IFERROR($I9/$E9,0) -> 0
A10: R06 | B10: Reader 06 | C10: T3 | D10: Training: SFT, LoRA/PEFT, MoE adaptation, diversity, corpora | E10: =COUNTIF(Papers!$D:$D,$A10) -> 14 | F10: =COUNTIFS(Papers!$D:$D,$A10,Papers!$C:$C,1) -> 3 | G10: =COUNTIFS(Papers!$D:$D,$A10,Papers!$C:$C,2) -> 6 | H10: =COUNTIFS(Papers!$D:$D,$A10,Papers!$C:$C,3) -> 5 | I10: =COUNTIFS(Papers!$D:$D,$A10,Papers!$Q:$Q,"Done") -> 0 | J10: =IFERROR($I10/$E10,0) -> 0
A11: R07 | B11: Reader 07 | C11: T4 | D11: Contamination, leakage and decontaminated evaluation | E11: =COUNTIF(Papers!$D:$D,$A11) -> 14 | F11: =COUNTIFS(Papers!$D:$D,$A11,Papers!$C:$C,1) -> 6 | G11: =COUNTIFS(Papers!$D:$D,$A11,Papers!$C:$C,2) -> 5 | H11: =COUNTIFS(Papers!$D:$D,$A11,Papers!$C:$C,3) -> 3 | I11: =COUNTIFS(Papers!$D:$D,$A11,Papers!$Q:$Q,"Done") -> 0 | J11: =IFERROR($I11/$E11,0) -> 0
A12: R08 | B12: Reader 08 | C12: T4 | D12: Contamination, leakage and decontaminated evaluation | E12: =COUNTIF(Papers!$D:$D,$A12) -> 14 | F12: =COUNTIFS(Papers!$D:$D,$A12,Papers!$C:$C,1) -> 5 | G12: =COUNTIFS(Papers!$D:$D,$A12,Papers!$C:$C,2) -> 6 | H12: =COUNTIFS(Papers!$D:$D,$A12,Papers!$C:$C,3) -> 3 | I12: =COUNTIFS(Papers!$D:$D,$A12,Papers!$Q:$Q,"Done") -> 0 | J12: =IFERROR($I12/$E12,0) -> 0
A13: R09 | B13: Reader 09 | C13: T5 | D13: RL from verifiers, reward hacking and repair loops | E13: =COUNTIF(Papers!$D:$D,$A13) -> 10 | F13: =COUNTIFS(Papers!$D:$D,$A13,Papers!$C:$C,1) -> 6 | G13: =COUNTIFS(Papers!$D:$D,$A13,Papers!$C:$C,2) -> 2 | H13: =COUNTIFS(Papers!$D:$D,$A13,Papers!$C:$C,3) -> 2 | I13: =COUNTIFS(Papers!$D:$D,$A13,Papers!$Q:$Q,"Done") -> 0 | J13: =IFERROR($I13/$E13,0) -> 0
A14: R10 | B14: Reader 10 | C14: T5 | D14: RL from verifiers, reward hacking and repair loops | E14: =COUNTIF(Papers!$D:$D,$A14) -> 10 | F14: =COUNTIFS(Papers!$D:$D,$A14,Papers!$C:$C,1) -> 5 | G14: =COUNTIFS(Papers!$D:$D,$A14,Papers!$C:$C,2) -> 3 | H14: =COUNTIFS(Papers!$D:$D,$A14,Papers!$C:$C,3) -> 2 | I14: =COUNTIFS(Papers!$D:$D,$A14,Papers!$Q:$Q,"Done") -> 0 | J14: =IFERROR($I14/$E14,0) -> 0
D15: TOTAL | E15: =SUM(E5:E14) -> 125 | F15: =SUM(F5:F14) -> 44 | G15: =SUM(G5:G14) -> 49 | H15: =SUM(H5:H14) -> 32 | I15: =SUM(I5:I14) -> 0 | J15: =IFERROR(I15/E15,0) -> 0

Sheet Papers
A1: Papers - one row per paper. Columns Q onward are yours to fill; everything left of them is source metadata.
A2: ID | B2: Theme | C2: Pri | D2: Reader slot | E2: Reader name | F2: Title | G2: First author | H2: All authors | I2: Year | J2: Published | K2: Venue / notes | L2: Source | M2: Link | N2: Concern | O2: Why it matters to prove-TLA | P2: Question this should answer for us | Q2: Status | R2: Due | S2: Date completed | T2: Key takeaway (fill in) | U2: Actionable here? | V2: Cite in write-up? | W2: Notes link | X2: Reviewer notes
A3: P001 | B3: T1 | C3: 1 | D3: R01 | E3: =INDEX(Roster!$B$5:$B$14,MATCH($D3,Roster!$A$5:$A$14,0)) -> Reader 01 | F3: Specification and Verification with the TLA+ Trifecta: TLC, Apalache, and TLAPS | G3: Igor Konnov | H3: Igor Konnov; Markus Kuppe; Stephan Merz | I3: 2022 | J3: 2022-11-14 | K3: arXiv preprint | L3: arXiv:2211.07216 | M3: https://arxiv.org/abs/2211.07216 | N3: Background | O3: TLC vs Apalache vs TLAPS side by side; grounds why the harness stages are sany,tlc,tlaps and what Apalache would add. | P3: Would Apalache catch spec defects our TLC-plus-mutation battery misses? | Q3: Not started | R3: 46247
A4: P002 | B4: T1 | C4: 1 | D4: R02 | E4: =INDEX(Roster!$B$5:$B$14,MATCH($D4,Roster!$A$5:$A$14,0)) -> Reader 02 | F4: SysMoBench: Evaluating AI on Formally Modeling Complex Real-World Systems | G4: Qian Cheng | H4: Qian Cheng; Ruize Tang; Emilie Ma; Finn Hackett; Peiyang He; Yiming Su; Ivan Beschastnikh; Yu Huang; +2 more | I4: 2025 | J4: 2025-09-27 | K4: arXiv preprint | L4: arXiv:2509.23130 | M4: https://arxiv.org/abs/2509.23130 | N4: Contamination | O4: Benchmark for formally modeling complex real-world systems - a second decontaminated comparator that is not FormaLLM-derived. | P4: Can SysMoBench score G2 without inheriting our contamination problem? | Q4: Not started | R4: 46247
A5: P003 | B5: T1 | C5: 1 | D5: R01 | E5: =INDEX(Roster!$B$5:$B$14,MATCH($D5,Roster!$A$5:$A$14,0)) -> Reader 01 | F5: Towards Language Model Guided TLA+ Proof Automation | G5: Yuhao Zhou | H5: Yuhao Zhou; Stavros Tripakis | I5: 2025 | J5: 2025-12-10 | K5: arXiv preprint | L5: arXiv:2512.09758 | M5: https://arxiv.org/abs/2512.09758 | N5: Training | O5: Loop-only (no fine-tune) TLA+ proof automation on a 119-theorem bench; the honest 0/119 Stage-3 floor is measured against it. | P5: How much of their result is loop engineering versus base-model strength, and does their bench overlap our holdout? | Q5: Not started | R5: 46247
A6: P004 | B6: T1 | C6: 1 | D6: R02 | E6: =INDEX(Roster!$B$5:$B$14,MATCH($D6,Roster!$A$5:$A$14,0)) -> Reader 02 | F6: Can LLMs Write Correct TLA+ Specifications? Evaluating Natural-Language-to-TLA+ Generation | G6: Arslan Bisharat | H6: Arslan Bisharat; Brian Ortiz; Eric Spencer; Khushboo Bhadauria; TaiNing Wang; George K. Thiruvathukal; Konstantin Laufer; Mohammed Abuhamad | I6: 2026 | J6: 2026-06-04 | K6: 12 pages, 11 tables. Accepted at the 21st International Conference on Software Technologies (ICSOFT 2026); Recommended as Best Paper Award Candidate | L6: arXiv:2606.05792 | M6: https://arxiv.org/abs/2606.05792 | N6: Both | O6: The origin of the 205/206-spec corpus prove-TLA scores G1 on, and the 8.6% semantic-correctness baseline everything is compared against. | P6: Which of their 30 evaluated models had the 205 specs in pretraining, and does their semantic-correctness check do anything Rule 9 does not? | Q6: Not started | R6: 46247
A7: P005 | B7: T1 | C7: 1 | D7: R01 | E7: =INDEX(Roster!$B$5:$B$14,MATCH($D7,Roster!$A$5:$A$14,0)) -> Reader 01 | F7: TLA-Prover: Verifiable TLA+ Specification Synthesis via Preference-Optimized Low-Rank Adaptation | G7: Eric Spencer | H7: Eric Spencer; Arslan Bisharat; Brian Ortiz; Khushboo Bhadauria; Mujtaba Nazari; TaiNing Wang; George K. Thiruvathukal; Konstantin Laufer; +1 more | I7: 2026 | J7: 2026-06-04 | K7: 12 pages, 5 tables, 3 figures. In Proceedings at the 21st International Conference on Software Technologies (ICSOFT 2026) | L7: arXiv:2606.06133 | M7: https://arxiv.org/abs/2606.06133 | N7: Both | O7: The 30% Gold / 0-of-18-proved claim in PLAN G2, and the motivating case study: self-referential adapter, MoE experts untouched, training corpus overlapping the benchmark. | P7: Exactly which artifacts would we need from the authors to reproduce 30% Gold, and does the paper state its decontamination procedure at all? | Q7: Not started | R7: 46247
A8: P006 | B8: T1 | C8: 1 | D8: R02 | E8: =INDEX(Roster!$B$5:$B$14,MATCH($D8,Roster!$A$5:$A$14,0)) -> Reader 02 | F8: TLA+-Bench: An Execution-Grounded Benchmark and Dataset for Natural-Language to TLA+ Specification Generation | G8: Arslan Bisharat | H8: Arslan Bisharat; Eric Spencer; Brian Ortiz; Khushboo Bhadauria; Mujtaba Nazari; Beatriz Santos; Anisa Ramos; TaiNing Wang; +3 more | I8: 2026 | J8: 2026-07-26 | K8: 17 pages, appendix included. Introduces TLA+-Bench, an execution-grounded benchmark and dataset for natural-language to TLA$^{+}$ specification generation. Dataset, evaluation code | L8: arXiv:2607.23425 | M8: https://arxiv.org/abs/2607.23425 | N8: Contamination | O8: Execution-grounded NL-to-TLA+ benchmark graded by real SANY parse plus TLC check - the closest external instrument to our gen-eval, and a candidate for widening the 30-spec holdout. | P8: Is TLA+-Bench disjoint from the FormaLLM 206, and could it supply the 15 extra holdout specs the power analysis says we need? | Q8: Not started | R8: 46247
A9: P007 | B9: T1 | C9: 1 | D9: R01 | E9: =INDEX(Roster!$B$5:$B$14,MATCH($D9,Roster!$A$5:$A$14,0)) -> Reader 01 | F9: Specula: Scaling formal specifications for autonomous model checking of system code | G9: Qian Cheng | H9: Qian Cheng; Saad Mohammad Rafid Pial; Ruize Tang; Yiming Su; Emilie Ma; Finn Hackett; Ivan Beschastnikh; Yu Huang; +1 more | I9: 2026 | J9: 2026-07-28 | K9: 17 pages, 11 figures | L9: arXiv:2607.25333 | M9: https://arxiv.org/abs/2607.25333 | N9: Training | O9: Agentic TLA+ spec generation at industrial scale (48 projects, 249 bugs) using self-evolving loops aimed squarely at reward hacking - the loop-not-weights thesis, validated externally. | P9: What do their self-evolving loops check that our mutation/vacuity battery does not, and did they need any fine-tuning at all? | Q9: Not started | R9: 46247
A10: P008 | B10: T1 | C10: 2 | D10: R02 | E10: =INDEX(Roster!$B$5:$B$14,MATCH($D10,Roster!$A$5:$A$14,0)) -> Reader 02 | F10: Model Checking TLA+ Specifications | G10: Yuan Yu | H10: Yuan Yu; Panagiotis Manolios; Leslie Lamport | I10: 1999 | J10: 1999-09-27 | K10: CHARME 1999, LNCS 1703 | L10: peer-reviewed | M10: https://link.springer.com/chapter/10.1007/3-540-48153-2_6 | N10: Background | O10: The original TLC paper (Yu, Manolios, Lamport, CHARME 1999) - what TLC does and does not guarantee. | P10: What exactly does a TLC pass entitle us to claim, before the vacuity battery runs? | Q10: Not started | R10: 46268
A11: P009 | B11: T1 | C11: 2 | D11: R01 | E11: =INDEX(Roster!$B$5:$B$14,MATCH($D11,Roster!$A$5:$A$14,0)) -> Reader 01 | F11: Vacuity Detection in Temporal Model Checking | G11: Orna Kupferman | H11: Orna Kupferman; Moshe Y. Vardi | I11: 2003 | J11: 2003-02-01 | K11: STTT 4(2) | L11: peer-reviewed | M11: https://link.springer.com/article/10.1007/s100090100062 | N11: Background | O11: Kupferman and Vardi on vacuity detection - the theoretical basis for Rule 9 and the mutation battery. | P11: Is our mutation battery a sound approximation of vacuity detection, or just a heuristic? | Q11: Not started | R11: 46268
A12: P010 | B12: T1 | C12: 2 | D12: R02 | E12: =INDEX(Roster!$B$5:$B$14,MATCH($D12,Roster!$A$5:$A$14,0)) -> Reader 02 | F12: How Amazon Web Services Uses Formal Methods | G12: Chris Newcombe | H12: Chris Newcombe; Tim Rath; Fan Zhang; Bogdan Munteanu; Marc Brooker; Michael Deardeuff | I12: 2015 | J12: 2015-04-01 | K12: CACM 58(4) | L12: peer-reviewed | M12: https://cacm.acm.org/research/how-amazon-web-services-uses-formal-methods/ | N12: Background | O12: Newcombe et al.'s account of TLA+ in production at AWS - the standing argument for why any of this matters commercially. | P12: Which failure classes did TLA+ actually catch at AWS, and are those classes represented in our corpus? | Q12: Not started | R12: 46268
A13: P011 | B13: T1 | C13: 2 | D13: R01 | E13: =INDEX(Roster!$B$5:$B$14,MATCH($D13,Roster!$A$5:$A$14,0)) -> Reader 01 | F13: TLA+ Model Checking Made Symbolic | G13: Igor Konnov | H13: Igor Konnov; Jure Kukovec; Thanh-Hai Tran | I13: 2019 | J13: 2019-10-10 | K13: OOPSLA 2019 / PACMPL 3 | L13: peer-reviewed | M13: https://dl.acm.org/doi/10.1145/3360549 | N13: Background | O13: The Apalache symbolic model checker (OOPSLA 2019); the SMT-based alternative to TLC's explicit enumeration. | P13: Would symbolic checking change which of the 30 unclosed specs are reachable? | Q13: Not started | R13: 46268
A14: P012 | B14: T1 | C14: 2 | D14: R02 | E14: =INDEX(Roster!$B$5:$B$14,MATCH($D14,Roster!$A$5:$A$14,0)) -> Reader 02 | F14: Plain and Simple Inductive Invariant Inference for Distributed Protocols in TLA+ | G14: William Schultz | H14: William Schultz; Ian Dardik; Stavros Tripakis | I14: 2022 | J14: 2022-05-12 | K14: arXiv preprint | L14: arXiv:2205.06360 | M14: https://arxiv.org/abs/2205.06360 | N14: Background | O14: Non-LLM inductive invariant inference for TLA+ - the symbolic baseline any learned approach has to beat. | P14: On which specs does plain enumeration already win, and should those be excluded from a capability claim? | Q14: Not started | R14: 46268
... A127: P125 | B127: T5 | C127: 3 | D127: R10 | E127: =INDEX(Roster!$B$5:$B$14,MATCH($D127,Roster!$A$5:$A$14,0)) -> Reader 10 | F127: SCOPE: Leveraging Subgoal Critiques for Code Generation | G127: Yueke Zhang | H127: Yueke Zhang; Yifan Zhang; Zihan Fang; Kevin Leach; Wei Zhang; Yu Huang | I127: 2026 | J127: 2026-07-07 | K127: arXiv preprint | L127: arXiv:2607.05810 | M127: https://arxiv.org/abs/2607.05810 | N127: Training | O127: Subgoal critiques for code generation. | P127: Do subgoal critiques map onto spec sub-components (init, next, invariant)? | Q127: Not started | R127: 46289

Sheet Themes
A1: Themes - what each pair of readers owns
A3: Theme | B3: Name | C3: Readers | D3: Papers | E3: P1 | F3: Maps to concern | G3: The question this theme owns
A4: T1 | B4: TLA+, model checking and the toolchain | C4: R01, R02 | D4: =COUNTIF(Papers!$B:$B,$A4) -> 21 | E4: =COUNTIFS(Papers!$B:$B,$A4,Papers!$C:$C,1) -> 7 | F4: Both (state of the art) | G4: How TLA+ specs, TLC/SANY/Apalache/TLAPS, and LLM-driven spec work actually behave. Owns the question: what is the state of the art we must beat, and is any of it measured honestly?
A5: T2 | B5: LLMs x formal verification beyond TLA+ | C5: R03, R04 | D5: =COUNTIF(Papers!$B:$B,$A5) -> 27 | E5: =COUNTIFS(Papers!$B:$B,$A5,Papers!$C:$C,1) -> 8 | F5: Both (method transfer) | G5: Dafny, Verus, Lean, F*, and autoformalization. Owns the question: what has worked in neighbouring formal languages that we have not tried, especially on spec faithfulness.
A6: T3 | B6: Training: SFT, LoRA/PEFT, MoE adaptation, diversity, corpora | C6: R05, R06 | D6: =COUNTIF(Papers!$B:$B,$A6) -> 29 | E6: =COUNTIFS(Papers!$B:$B,$A6,Papers!$C:$C,1) -> 7 | F6: (1) Training | G6: Concern (1). Owns the question: was the fine-tuning failure a method problem, a corpus problem, or a broken adapter - and what would a correct MoE LoRA setup look like.
A7: T4 | B7: Contamination, leakage and decontaminated evaluation | C7: R07, R08 | D7: =COUNTIF(Papers!$B:$B,$A7) -> 28 | E7: =COUNTIFS(Papers!$B:$B,$A7,Papers!$C:$C,1) -> 11 | F7: (2) Contamination | G7: Concern (2). Owns the question: how do we prove a holdout is clean, how contaminated is the 206-spec corpus, and what claims does that permit.
A8: T5 | B8: RL from verifiers, reward hacking and repair loops | C8: R09, R10 | D8: =COUNTIF(Papers!$B:$B,$A8) -> 20 | E8: =COUNTIFS(Papers!$B:$B,$A8,Papers!$C:$C,1) -> 11 | F8: (1) + (2) bridge | G8: The bridge between (1) and (2). Owns the question: when you train against a checker, when is the model learning the task and when is it learning the checker's blind spots.
